locust_swarm/__init__.py
locust_swarm/__main__.py
locust_swarm/_version.py
locust_swarm/swarm.py
locust_swarm-6.1.1.dist-info/LICENSE
locust_swarm-6.1.1.dist-info/METADATA
locust_swarm-6.1.1.dist-info/WHEEL
locust_swarm-6.1.1.dist-info/entry_points.txt
locust_swarm-6.1.1.dist-info/top_level.txt
locust_swarm-6.1.1.dist-info/RECORD
